README.md
setup.py
py_scripts/__init__.py
py_scripts/py_replace.py
py_scripts.egg-info/PKG-INFO
py_scripts.egg-info/SOURCES.txt
py_scripts.egg-info/dependency_links.txt
py_scripts.egg-info/entry_points.txt
py_scripts.egg-info/not-zip-safe
py_scripts.egg-info/requires.txt
py_scripts.egg-info/top_level.txt