Metadata-Version: 2.1
Name: py-scripts
Version: 0.0.2
Summary: UNKNOWN
Home-page: https://github.com/dodoru/py_scripts
Author: Nico NR
Author-email: dodoru@foxmail.com
License: MIT
Platform: any
Classifier: License :: OSI Approved :: MIT License
Classifier: Operating System :: OS Independent
Classifier: Programming Language :: Python
Classifier: Programming Language :: Python :: 2.7
Classifier: Programming Language :: Python :: 3
Classifier: Programming Language :: Python :: 3.2
Classifier: Programming Language :: Python :: 3.3
Classifier: Programming Language :: Python :: 3.4
Classifier: Topic :: Utilities
Classifier: Development Status :: 4 - Beta
